NeuroPredPLM/__init__.py
NeuroPredPLM/args.pt
NeuroPredPLM/model.py
NeuroPredPLM/predict.py
NeuroPredPLM/utils.py
NeuroPredPLM-0.1.0.dist-info/LICENSE
NeuroPredPLM-0.1.0.dist-info/METADATA
NeuroPredPLM-0.1.0.dist-info/WHEEL
NeuroPredPLM-0.1.0.dist-info/top_level.txt
NeuroPredPLM-0.1.0.dist-info/RECORD
