Metadata-Version: 2.1
Name: NeuroPredPLM
Version: 0.1.0
Summary: an interpretable and robust model for neuropeptide prediction by protein language model
Home-page: http://github.com/isyslab-hust/NeuroPred-PLM
Author: Lei Wang
Author-email: wanglei94@hust.edu.cn
License: MIT
Keywords: neuropeptide prediction
Classifier: Development Status :: 3 - Alpha
Classifier: Intended Audience :: Developers
Classifier: License :: OSI Approved :: MIT License
Classifier: Programming Language :: Python :: 3
License-File: LICENSE
Requires-Dist: einops
Requires-Dist: fair-esm
Requires-Dist: torch
Requires-Dist: numpy
